plone.app.mosaic-2.2.5-py3.9-nspkg.pth
plone/app/mosaic/__init__.py
plone/app/mosaic/configure.zcml
plone/app/mosaic/forms.py
plone/app/mosaic/handlers.py
plone/app/mosaic/index.py
plone/app/mosaic/interfaces.py
plone/app/mosaic/layoutpolicy.py
plone/app/mosaic/layouts.zcml
plone/app/mosaic/registry.py
plone/app/mosaic/setuphandlers.py
plone/app/mosaic/sitelayouts-bs3demo.zcml
plone/app/mosaic/sitelayouts-meta.zcml
plone/app/mosaic/testing.py
plone/app/mosaic/transform.py
plone/app/mosaic/upgrades.py
plone/app/mosaic/upgrades.zcml
plone/app/mosaic/utils.py
plone/app/mosaic/widget.py
plone/app/mosaic/browser/__init__.py
plone/app/mosaic/browser/configure.zcml
plone/app/mosaic/browser/editor.py
plone/app/mosaic/browser/layoutmenu.py
plone/app/mosaic/browser/layoutmenu.zcml
plone/app/mosaic/browser/main_template.py
plone/app/mosaic/browser/upload.py
plone/app/mosaic/browser/static/layouts-editor.css
plone/app/mosaic/browser/static/layouts-editor.js
plone/app/mosaic/browser/static/mosaic-grid.css
plone/app/mosaic/browser/static/mosaic-grid.js
plone/app/mosaic/browser/static/mosaic-styles.css
plone/app/mosaic/browser/static/mosaic-styles.js
plone/app/mosaic/browser/static/plone-mosaic.css
plone/app/mosaic/browser/static/plone-mosaic.js
plone/app/mosaic/browser/static/css/layouts-editor.less
plone/app/mosaic/browser/static/css/mosaic.authoring.dividers.less
plone/app/mosaic/browser/static/css/mosaic.authoring.dragging.less
plone/app/mosaic/browser/static/css/mosaic.authoring.overlays.less
plone/app/mosaic/browser/static/css/mosaic.authoring.resizing.less
plone/app/mosaic/browser/static/css/mosaic.authoring.tiles.less
plone/app/mosaic/browser/static/css/mosaic.grid.less
plone/app/mosaic/browser/static/css/mosaic.layouts.less
plone/app/mosaic/browser/static/css/mosaic.pattern.less
plone/app/mosaic/browser/static/css/mosaic.styles.less
plone/app/mosaic/browser/static/css/mosaic.tinymce.less
plone/app/mosaic/browser/static/css/mosaic.toolbar.less
plone.app.mosaic-2.2.5.dist-info/LICENSE
plone.app.mosaic-2.2.5.dist-info/METADATA
plone.app.mosaic-2.2.5.dist-info/WHEEL
plone.app.mosaic-2.2.5.dist-info/entry_points.txt
plone.app.mosaic-2.2.5.dist-info/namespace_packages.txt
plone.app.mosaic-2.2.5.dist-info/top_level.txt
plone.app.mosaic-2.2.5.dist-info/RECORD
