Metadata-Version: 2.1
Name: plone.app.mosaic
Version: 2.2.5
Summary: Plone Mosaic Site Builder and Site Layout
Home-page: https://github.com/plone/plone.app.mosaic
Author: The Plone Community
Author-email: foundation@plone.org
License: gpl
Keywords: site builder collage
Platform: UNKNOWN
Classifier: Development Status :: 5 - Production/Stable
Classifier: Environment :: Web Environment
Classifier: Framework :: Plone
Classifier: Framework :: Plone :: 5.1
Classifier: Framework :: Plone :: 5.2
Classifier: License :: OSI Approved :: GNU General Public License v2 (GPLv2)
Classifier: Programming Language :: Python
Classifier: Programming Language :: Python :: 2.7
Classifier: Programming Language :: Python :: 3.6
Classifier: Programming Language :: Python :: 3.7
Classifier: Topic :: Internet :: WWW/HTTP
Classifier: Topic :: Internet :: WWW/HTTP :: Dynamic Content
Classifier: Topic :: Software Development :: Libraries :: Python Modules
License-File: LICENSE
Requires-Dist: setuptools
Requires-Dist: six
Requires-Dist: plone.subrequest (>=1.8.6)
Requires-Dist: plone.tiles (>=2.2.0)
Requires-Dist: plone.app.blocks (>=4.3.1)
Requires-Dist: plone.app.tiles (>=3.1.1)
Requires-Dist: plone.app.drafts (>=1.1.3)
Requires-Dist: plone.app.standardtiles (>=2.3.1)
Requires-Dist: Products.CMFPlone (>=5.1)
Requires-Dist: plone.app.layout
Requires-Dist: plone.app.contenttypes (>=2.0.0)
Requires-Dist: plone.behavior (>=1.3.0)
Provides-Extra: test
Requires-Dist: plone.app.testing ; extra == 'test'
Requires-Dist: plone.app.contenttypes ; extra == 'test'
Requires-Dist: plone.app.widgets (>=1.8.0.dev0) ; extra == 'test'
Requires-Dist: plone.app.robotframework ; extra == 'test'
Requires-Dist: robotframework-selenium2library ; extra == 'test'
Requires-Dist: robotframework-selenium2screenshots ; extra == 'test'
